[
  {
    "valid": ["luzi82", "hcsvfqyatttndvretmcv"],
    "source": "http://www.luzi82.com/~luzi82/v1/live/live092000.htm",
    "invalid": [],
    "approved": true,
    "sentence": "不斷勤加苦讀",
    "username": "luzi82",
    "createdAt": 1561182693910,
    "approvalDate": 1562258794488,
    "Sentences_Meta_UserVote_luzi82": true,
    "Sentences_Meta_UserVoteDate_luzi82": 1561182988433,
    "Sentences_Meta_UserVote_hcsvfqyatttndvretmcv": true,
    "Sentences_Meta_UserVoteDate_hcsvfqyatttndvretmcv": 1562258794488,
    "id": "9ae219d2eba64339e0771e36333bd91fec910ae459abfa9d1aa32c2d34ff0bd0",
    "last_modified": 1562258795303
  },
  {
    "valid": ["luzi82", "hcsvfqyatttndvretmcv"],
    "source": "http://www.luzi82.com/~luzi82/v1/live/live092000.htm",
    "invalid": [],
    "approved": true,
    "sentence": "甚至為左能夠喺下一個學年再見到佢",
    "username": "luzi82",
    "createdAt": 1561182681637,
    "approvalDate": 1562258794488,
    "Sentences_Meta_UserVote_luzi82": true,
    "Sentences_Meta_UserVoteDate_luzi82": 1561182988433,
    "Sentences_Meta_UserVote_hcsvfqyatttndvretmcv": true,
    "Sentences_Meta_UserVoteDate_hcsvfqyatttndvretmcv": 1562258794488,
    "id": "934d84d8b3a5736c3d701888cea8c2640be17ec1bbd2d5537a790481e36f8e83",
    "last_modified": 1562258795290
  },
  {
    "valid": ["luzi82", "hcsvfqyatttndvretmcv"],
    "source": "http://www.luzi82.com/~luzi82/v1/live/live092000.htm",
    "invalid": [],
    "approved": true,
    "sentence": "我竟然對佢產生左一份特別嘅感情",
    "username": "luzi82",
    "createdAt": 1561181869483,
    "approvalDate": 1562258794488,
    "Sentences_Meta_UserVote_luzi82": true,
    "Sentences_Meta_UserVoteDate_luzi82": 1561182988433,
    "Sentences_Meta_UserVote_hcsvfqyatttndvretmcv": true,
    "Sentences_Meta_UserVoteDate_hcsvfqyatttndvretmcv": 1562258794488,
    "id": "5fe402056ee8b5cbe3192d8c220b4a32cae7c9ce897e515ea1de2a735345afae",
    "last_modified": 1562258795276
  },
  {
    "valid": ["luzi82", "hcsvfqyatttndvretmcv"],
    "source": "http://www.luzi82.com/~luzi82/v1/live/live092000.htm",
    "invalid": [],
    "approved": true,
    "sentence": "久而久之",
    "username": "luzi82",
    "createdAt": 1561181844310,
    "approvalDate": 1562258794488,
    "Sentences_Meta_UserVote_luzi82": true,
    "Sentences_Meta_UserVoteDate_luzi82": 1561182988433,
    "Sentences_Meta_UserVote_hcsvfqyatttndvretmcv": true,
    "Sentences_Meta_UserVoteDate_hcsvfqyatttndvretmcv": 1562258794488,
    "id": "6f48cd1cc2fea63265b47fe8096cefd40275a4ff1246e38ebd0d6a0d4a98f0dc",
    "last_modified": 1562258795264
  },
  {
    "valid": ["luzi82", "hcsvfqyatttndvretmcv"],
    "source": "http://www.luzi82.com/~luzi82/v1/live/live092000.htm",
    "invalid": [],
    "approved": true,
    "sentence": "起初因為意志消沉而不斷整蠱佢",
    "username": "luzi82",
    "createdAt": 1561179996699,
    "approvalDate": 1562258794488,
    "Sentences_Meta_UserVote_luzi82": true,
    "Sentences_Meta_UserVoteDate_luzi82": 1561182988433,
    "Sentences_Meta_UserVote_hcsvfqyatttndvretmcv": true,
    "Sentences_Meta_UserVoteDate_hcsvfqyatttndvretmcv": 1562258794488,
    "id": "a2706a603dbe18c0237d079fbd39d003773f55a88dc896e6b36f061733883ce2",
    "last_modified": 1562258795251
  },
  {
    "valid": ["luzi82", "hcsvfqyatttndvretmcv"],
    "source": "http://www.luzi82.com/~luzi82/v1/live/live092000.htm",
    "invalid": [],
    "approved": true,
    "sentence": "我喺圖書館識左佢",
    "username": "luzi82",
    "createdAt": 1561179950276,
    "approvalDate": 1562258794488,
    "Sentences_Meta_UserVote_luzi82": true,
    "Sentences_Meta_UserVoteDate_luzi82": 1561182980630,
    "Sentences_Meta_UserVote_hcsvfqyatttndvretmcv": true,
    "Sentences_Meta_UserVoteDate_hcsvfqyatttndvretmcv": 1562258794488,
    "id": "661e9aec8f853d7550a3d0f7408d7571c81c87c9a0e79155e2c1da2b8e41c0bb",
    "last_modified": 1562258795238
  },
  {
    "valid": ["luzi82", "hcsvfqyatttndvretmcv"],
    "source": "http://www.luzi82.com/~luzi82/v1/live/live092000.htm",
    "invalid": [],
    "approved": true,
    "sentence": "同一時間",
    "username": "luzi82",
    "createdAt": 1561179922223,
    "approvalDate": 1562258794488,
    "Sentences_Meta_UserVote_luzi82": true,
    "Sentences_Meta_UserVoteDate_luzi82": 1561182980630,
    "Sentences_Meta_UserVote_hcsvfqyatttndvretmcv": true,
    "Sentences_Meta_UserVoteDate_hcsvfqyatttndvretmcv": 1562258794488,
    "id": "a5437c804b28b460fb8cfb69aad3d567ded0bfaa14082105df5fb949b8098d4f",
    "last_modified": 1562258795223
  },
  {
    "valid": ["luzi82", "hcsvfqyatttndvretmcv"],
    "source": "http://www.luzi82.com/~luzi82/v1/live/live092000.htm",
    "invalid": [],
    "approved": true,
    "sentence": "學習生涯面臨考驗",
    "username": "luzi82",
    "createdAt": 1561179817746,
    "approvalDate": 1562258794488,
    "Sentences_Meta_UserVote_luzi82": true,
    "Sentences_Meta_UserVoteDate_luzi82": 1561182980630,
    "Sentences_Meta_UserVote_hcsvfqyatttndvretmcv": true,
    "Sentences_Meta_UserVoteDate_hcsvfqyatttndvretmcv": 1562258794488,
    "id": "06575cb7761b9d5c4c95fb482f19bbeb29fc06e498a3462253ebdbf5ec2df1ba",
    "last_modified": 1562258795209
  },
  {
    "valid": ["luzi82", "hcsvfqyatttndvretmcv"],
    "source": "http://www.luzi82.com/~luzi82/v1/live/live092000.htm",
    "invalid": [],
    "approved": true,
    "sentence": "令我唔習慣新嘅學校生活",
    "username": "luzi82",
    "createdAt": 1561179756020,
    "approvalDate": 1562258794488,
    "Sentences_Meta_UserVote_luzi82": true,
    "Sentences_Meta_UserVoteDate_luzi82": 1561182980630,
    "Sentences_Meta_UserVote_hcsvfqyatttndvretmcv": true,
    "Sentences_Meta_UserVoteDate_hcsvfqyatttndvretmcv": 1562258794488,
    "id": "5f5831f30cf2e965c08eeff972b3c30319b6b0f6d9feef8fbdbe70bf69242c00",
    "last_modified": 1562258795195
  },
  {
    "valid": ["luzi82", "hcsvfqyatttndvretmcv"],
    "source": "http://www.luzi82.com/~luzi82/v1/live/live092000.htm",
    "invalid": [],
    "approved": true,
    "sentence": "加上我唔識得同新同學打交道",
    "username": "luzi82",
    "createdAt": 1561179732499,
    "approvalDate": 1562258794488,
    "Sentences_Meta_UserVote_luzi82": true,
    "Sentences_Meta_UserVoteDate_luzi82": 1561182980630,
    "Sentences_Meta_UserVote_hcsvfqyatttndvretmcv": true,
    "Sentences_Meta_UserVoteDate_hcsvfqyatttndvretmcv": 1562258794488,
    "id": "d3ea7dd5a4418931aac4edd58d01d757c671337d7a5b3f104aca9677b4a36213",
    "last_modified": 1562258795181
  },
  {
    "valid": ["luzi82", "hcsvfqyatttndvretmcv"],
    "source": "http://www.luzi82.com/~luzi82/v1/live/live092000.htm",
    "invalid": [],
    "approved": true,
    "sentence": "使我嘅社交生活受到好大影響",
    "username": "luzi82",
    "createdAt": 1561179695957,
    "approvalDate": 1562258794488,
    "Sentences_Meta_UserVote_luzi82": true,
    "Sentences_Meta_UserVoteDate_luzi82": 1561182970320,
    "Sentences_Meta_UserVote_hcsvfqyatttndvretmcv": true,
    "Sentences_Meta_UserVoteDate_hcsvfqyatttndvretmcv": 1562258794488,
    "id": "86c301e55aadb4c121631fe68e9052c0f8b9d384944ef16a8877ee6b62cd210f",
    "last_modified": 1562258795167
  },
  {
    "valid": ["luzi82", "hcsvfqyatttndvretmcv"],
    "source": "http://www.luzi82.com/~luzi82/v1/live/live092000.htm",
    "invalid": [],
    "approved": true,
    "sentence": "因為果陣絕大部分嘅同學都轉校",
    "username": "luzi82",
    "createdAt": 1561179659789,
    "approvalDate": 1562258794488,
    "Sentences_Meta_UserVote_luzi82": true,
    "Sentences_Meta_UserVoteDate_luzi82": 1561182970320,
    "Sentences_Meta_UserVote_hcsvfqyatttndvretmcv": true,
    "Sentences_Meta_UserVoteDate_hcsvfqyatttndvretmcv": 1562258794488,
    "id": "b842bd9e4e22f1a80b57b3528ca462c1130b962d048a546f8f23c912f248e8c5",
    "last_modified": 1562258795153
  },
  {
    "valid": ["luzi82", "hcsvfqyatttndvretmcv"],
    "source": "http://www.luzi82.com/~luzi82/v1/live/live092000.htm",
    "invalid": [],
    "approved": true,
    "sentence": "唯有原校重讀中五",
    "username": "luzi82",
    "createdAt": 1561179611517,
    "approvalDate": 1562258794488,
    "Sentences_Meta_UserVote_luzi82": true,
    "Sentences_Meta_UserVoteDate_luzi82": 1561182970320,
    "Sentences_Meta_UserVote_hcsvfqyatttndvretmcv": true,
    "Sentences_Meta_UserVoteDate_hcsvfqyatttndvretmcv": 1562258794488,
    "id": "dfcafc6da84e8fdb5d2c0090ae9a3ea61a1c02049562a911fc63bb87793f2879",
    "last_modified": 1562258795127
  },
  {
    "valid": ["luzi82", "hcsvfqyatttndvretmcv"],
    "source": "http://www.luzi82.com/~luzi82/v1/live/live092000.htm",
    "invalid": [],
    "approved": true,
    "sentence": "一九九九年",
    "username": "luzi82",
    "createdAt": 1561179597586,
    "approvalDate": 1562258794488,
    "Sentences_Meta_UserVote_luzi82": true,
    "Sentences_Meta_UserVoteDate_luzi82": 1561182970320,
    "Sentences_Meta_UserVote_hcsvfqyatttndvretmcv": true,
    "Sentences_Meta_UserVoteDate_hcsvfqyatttndvretmcv": 1562258794488,
    "id": "d232cd1364f5696d077fed2b86a4b197371a1ef06d4dd551bbb29e778855991b",
    "last_modified": 1562258795112
  },
  {
    "valid": ["luzi82", "hcsvfqyatttndvretmcv"],
    "source": "http://www.luzi82.com/~luzi82/v1/live/live092000.htm",
    "invalid": [],
    "approved": true,
    "sentence": "升唔到上中六",
    "username": "luzi82",
    "createdAt": 1561179578746,
    "approvalDate": 1562258794488,
    "Sentences_Meta_UserVote_luzi82": true,
    "Sentences_Meta_UserVoteDate_luzi82": 1561182970320,
    "Sentences_Meta_UserVote_hcsvfqyatttndvretmcv": true,
    "Sentences_Meta_UserVoteDate_hcsvfqyatttndvretmcv": 1562258794488,
    "id": "9ded065c218c7c8b6a5d4dc283331a6364f39ddbcd3a4d85ad3b641cd3a38af2",
    "last_modified": 1562258795099
  },
  {
    "valid": ["luzi82", "hcsvfqyatttndvretmcv"],
    "source": "http://www.luzi82.com/~luzi82/v1/live/live092000.htm",
    "invalid": [],
    "approved": true,
    "sentence": "我因為會考成績唔係咁好",
    "username": "luzi82",
    "createdAt": 1561179563836,
    "approvalDate": 1562258794488,
    "Sentences_Meta_UserVote_luzi82": true,
    "Sentences_Meta_UserVoteDate_luzi82": 1561182949224,
    "Sentences_Meta_UserVote_hcsvfqyatttndvretmcv": true,
    "Sentences_Meta_UserVoteDate_hcsvfqyatttndvretmcv": 1562258794488,
    "id": "dd23927a109c8b12931e6ccf31f3ab22f7682468157e69a8401a95069403907b",
    "last_modified": 1562258795084
  },
  {
    "valid": ["Allen", "johnjaller", "testa"],
    "source": "Me, things that I would say",
    "invalid": [],
    "approved": true,
    "sentence": "人冇夢想，同鹹魚有咩分別",
    "username": "tylerinq",
    "createdAt": 1554405626442,
    "approvalDate": 1556888670864,
    "Sentences_Meta_UserVote_Allen": true,
    "Sentences_Meta_UserVote_testa": true,
    "Sentences_Meta_UserVoteDate_Allen": 1554516376293,
    "Sentences_Meta_UserVoteDate_testa": 1556888670864,
    "Sentences_Meta_UserVote_johnjaller": true,
    "Sentences_Meta_UserVoteDate_johnjaller": 1555571044689,
    "id": "a1854ce97e7fd89b8d1da322f86c5fa4b01940f93793d938ec7ed99b38186a9c",
    "last_modified": 1556888671924
  },
  {
    "valid": ["Allen", "johnjaller", "testa"],
    "source": "Me, things that I would say",
    "invalid": [],
    "approved": true,
    "sentence": "你今日食咗飯未呀？",
    "username": "tylerinq",
    "createdAt": 1554405626441,
    "approvalDate": 1556888670864,
    "Sentences_Meta_UserVote_Allen": true,
    "Sentences_Meta_UserVote_testa": true,
    "Sentences_Meta_UserVoteDate_Allen": 1554516373271,
    "Sentences_Meta_UserVoteDate_testa": 1556888670864,
    "Sentences_Meta_UserVote_johnjaller": true,
    "Sentences_Meta_UserVoteDate_johnjaller": 1555571044689,
    "id": "dfed53dae4ab2526e092554201ac032ad27f8c1a1ce6bbd0f7304d67cd8e9a6e",
    "last_modified": 1556888671899
  },
  {
    "valid": ["Allen", "johnjaller", "testa"],
    "source": "Me, things that I would say",
    "invalid": [],
    "approved": true,
    "sentence": "我好想同你出去睇戲。",
    "username": "tylerinq",
    "createdAt": 1554405626441,
    "approvalDate": 1556888670864,
    "Sentences_Meta_UserVote_Allen": true,
    "Sentences_Meta_UserVote_testa": true,
    "Sentences_Meta_UserVoteDate_Allen": 1554516373271,
    "Sentences_Meta_UserVoteDate_testa": 1556888670864,
    "Sentences_Meta_UserVote_johnjaller": true,
    "Sentences_Meta_UserVoteDate_johnjaller": 1555571044689,
    "id": "8ccdb7d658ea10a53d9490b9831d74502d4ca249ad397569d99e050e7d850475",
    "last_modified": 1556888671876
  },
  {
    "valid": ["Allen", "johnjaller", "testa"],
    "source": "Me, things that I would say",
    "invalid": [],
    "approved": true,
    "sentence": "香港嘅「共享創意」同港大法律系有掛鉤",
    "username": "tylerinq",
    "createdAt": 1554405626440,
    "approvalDate": 1556888670864,
    "Sentences_Meta_UserVote_Allen": true,
    "Sentences_Meta_UserVote_testa": true,
    "Sentences_Meta_UserVoteDate_Allen": 1554516373271,
    "Sentences_Meta_UserVoteDate_testa": 1556888670864,
    "Sentences_Meta_UserVote_johnjaller": true,
    "Sentences_Meta_UserVoteDate_johnjaller": 1555571044689,
    "id": "c6a95cfa6295e124c34e7bda5fdaf13e79a40296137efbbef1639ceb38c9f4cd",
    "last_modified": 1556888671851
  }
]
