[{"valid":["aasami","tonydamage"],"source":"I am the sole author of these sentences.","invalid":[],"approved":true,"sentence":"Budete disponovať potrebným vybavením na bezproblémový chod spoločnosti.","username":"aasami","createdAt":1573205701579,"approvalDate":1577999148907,"Sentences_Meta_UserVote_aasami":true,"Sentences_Meta_UserVote_tonydamage":true,"Sentences_Meta_UserVoteDate_tonydamage":1577999148907,"id":"2b7601ab1af86f2ee0c6ec06580567cd3cdd956453b930a858dcef80fb3dfed0","last_modified":1577999149647},{"valid":["aasami","tonydamage"],"source":"I am the sole author of these sentences.","invalid":[],"approved":true,"sentence":"Dá sa zvýšiť rýchlosť a odozva poskytovaných služieb?","username":"aasami","createdAt":1573205701578,"approvalDate":1577999148907,"Sentences_Meta_UserVote_aasami":true,"Sentences_Meta_UserVote_tonydamage":true,"Sentences_Meta_UserVoteDate_tonydamage":1577999148907,"id":"06339ee9db64e89a93d24475fae0243e026c214b687925b4d05cfeb5f3806e63","last_modified":1577999149617},{"valid":["aasami","tonydamage"],"source":"I am the sole author of these sentences.","invalid":[],"approved":true,"sentence":"Pre ďalší rozvoj je potrebné nahradiť zastarané serverové vybavenie.","username":"aasami","createdAt":1573205701577,"approvalDate":1577999148906,"Sentences_Meta_UserVote_aasami":true,"Sentences_Meta_UserVote_tonydamage":true,"Sentences_Meta_UserVoteDate_tonydamage":1577999148906,"id":"c2e04224ed7d020dfc6f41cc6d9cd43613dec13aff843145c8ad5d182e7c4591","last_modified":1577999149592},{"valid":["aasami","tonydamage"],"source":"I am the sole author of these sentences.","invalid":[],"approved":true,"sentence":"Administrátori musia disponovať technickými zdatnosťami z viacerých oblastí.","username":"aasami","createdAt":1573205701574,"approvalDate":1577999148906,"Sentences_Meta_UserVote_aasami":true,"Sentences_Meta_UserVote_tonydamage":true,"Sentences_Meta_UserVoteDate_tonydamage":1577999148906,"id":"949386b7f999210886206c88e81432e21633dd45895d17997f6d0cc4190190ac","last_modified":1577999149536},{"valid":["aasami","tonydamage"],"source":"I am the sole author of these sentences.","invalid":[],"approved":true,"sentence":"Akákoľvek údržba systému je v danom prípade náročná.","username":"aasami","createdAt":1573205701573,"approvalDate":1577999148906,"Sentences_Meta_UserVote_aasami":true,"Sentences_Meta_UserVote_tonydamage":true,"Sentences_Meta_UserVoteDate_tonydamage":1577999148906,"id":"ac4d9da56ffb1ea63963e771914d87137210deaf0ccac9fd9f4f4a50c4dd253f","last_modified":1577999149441},{"valid":["aasami","tonydamage"],"source":"I am the sole author of these sentences.","invalid":[],"approved":true,"sentence":"Staré diskové polia sú doslova produkty z minulého storočia.","username":"aasami","createdAt":1573205701553,"approvalDate":1577999148906,"Sentences_Meta_UserVote_aasami":true,"Sentences_Meta_UserVote_tonydamage":true,"Sentences_Meta_UserVoteDate_tonydamage":1577999148906,"id":"9fd216c6801117bdb023114d4ad047e02e4476133411adb4773af38aae516f6d","last_modified":1577999149388},{"valid":["aasami","tonydamage"],"source":"I am the sole author of these sentences.","invalid":[],"approved":true,"sentence":"Generačná výmena hardvéru je preto pomerne náročná.","username":"aasami","createdAt":1573205701565,"approvalDate":1577999055365,"Sentences_Meta_UserVote_aasami":true,"Sentences_Meta_UserVote_tonydamage":true,"Sentences_Meta_UserVoteDate_tonydamage":1577999055365,"id":"30f967634d4b4df1b5bf2a775c7544a5d121eaf637ca1a21015646063153347f","last_modified":1577999056343},{"valid":["aasami","tonydamage"],"source":"I am the sole author of these sentences.","invalid":[],"approved":true,"sentence":"Hlavná serverovňa je pomerne malá čo obmedzuje ďalší rozvoj.","username":"aasami","createdAt":1573205701564,"approvalDate":1577999055365,"Sentences_Meta_UserVote_aasami":true,"Sentences_Meta_UserVote_tonydamage":true,"Sentences_Meta_UserVoteDate_tonydamage":1577999055365,"id":"50a3695f84a0858d2a9de440aeef07686460043f4c559fd011c1d6fd28f65584","last_modified":1577999056281},{"valid":["aasami","tonydamage"],"source":"I am the sole author of these sentences.","invalid":[],"approved":true,"sentence":"Aký je rozdiel medzi životom a smrťou?","username":"aasami","createdAt":1573205701538,"approvalDate":1577999055365,"Sentences_Meta_UserVote_aasami":true,"Sentences_Meta_UserVote_tonydamage":true,"Sentences_Meta_UserVoteDate_tonydamage":1577999055365,"id":"200f944afa863c4ce9ba3c0ce51ab8e2f874fc8248202d0f1cad2bb453ff99ca","last_modified":1577999056168},{"valid":["aasami","tonydamage"],"source":"I am the sole author of these sentences.","invalid":[],"approved":true,"sentence":"Treba robiť správne rozhodnutia, ktoré môžu znamenať ekonomickú výhodu.","username":"aasami","createdAt":1573205701535,"approvalDate":1577999055365,"Sentences_Meta_UserVote_aasami":true,"Sentences_Meta_UserVote_tonydamage":true,"Sentences_Meta_UserVoteDate_tonydamage":1577999055365,"id":"69bd64d499af64cb9bbb20a5b14549cbbb0e3f1d6b20a24a2e9653e238888540","last_modified":1577999056082},{"valid":["aasami","tonydamage"],"source":"I am the sole author of these sentences.","invalid":[],"approved":true,"sentence":"Informácie sa stali cennejšími ako zlato.","username":"aasami","createdAt":1573205701531,"approvalDate":1577999055365,"Sentences_Meta_UserVote_aasami":true,"Sentences_Meta_UserVote_tonydamage":true,"Sentences_Meta_UserVoteDate_tonydamage":1577999055365,"id":"b4613a58636bde3b37accb9d31e3c8fe3a7e027d022482502d3340b7d3ce5e9e","last_modified":1577999056009},{"valid":["aasami","tonydamage"],"source":"I am the sole author of these sentences.","invalid":[],"approved":true,"sentence":"Nároky na počet poskytovaných sieťových služieb v digitálnej spoločnosti neustále rastú.","username":"aasami","createdAt":1573205701528,"approvalDate":1577999055365,"Sentences_Meta_UserVote_aasami":true,"Sentences_Meta_UserVote_tonydamage":true,"Sentences_Meta_UserVoteDate_tonydamage":1577999055365,"id":"96d4e2f79c1319f97838bd659e45d341f795526f97894335d26ac55ad2d8f31a","last_modified":1577999055960},{"valid":["aasami","tonydamage"],"source":"I am the sole author of these sentences.","invalid":[],"approved":true,"sentence":"Za touto adresou sa nachádza niekoľko stoviek počítačov.","username":"aasami","createdAt":1573205701518,"approvalDate":1577999055365,"Sentences_Meta_UserVote_aasami":true,"Sentences_Meta_UserVote_tonydamage":true,"Sentences_Meta_UserVoteDate_tonydamage":1577999055365,"id":"ddd6a0e18777850345e3269ab721adc5670141908e143ad59e6e424d0da5e1f4","last_modified":1577999055937},{"valid":["aasami","tonydamage"],"source":"I am the sole author of these sentences.","invalid":[],"approved":true,"sentence":"Na základe adresy sa pokúsime lokalizovať človeka s možným malvérom v počítači.","username":"aasami","createdAt":1573205701512,"approvalDate":1577999055365,"Sentences_Meta_UserVote_aasami":true,"Sentences_Meta_UserVote_tonydamage":true,"Sentences_Meta_UserVoteDate_tonydamage":1577999055365,"id":"6f27a6737135f66d12ea98eede6315031ee02fc61deee1778f53aa275a9718f8","last_modified":1577999055904},{"valid":["aasami","tonydamage"],"source":"I am the sole author of these sentences.","invalid":[],"approved":true,"sentence":"Hlásenie o riešení ohrozenia bezpečnosti.","username":"aasami","createdAt":1573202375018,"approvalDate":1577999055365,"Sentences_Meta_UserVote_aasami":true,"Sentences_Meta_UserVote_tonydamage":true,"Sentences_Meta_UserVoteDate_tonydamage":1577999055365,"id":"19319a44d9a39bb07135bd2d95150b9597cccf47929abaf091267b0f102f4d3a","last_modified":1577999055831},{"valid":["aasami","tonydamage"],"source":"I am the sole author of these sentences.","invalid":[],"approved":true,"sentence":"V súčasnosti nemáme postačujúcu infraštruktúru.","username":"aasami","createdAt":1573202375018,"approvalDate":1577999055365,"Sentences_Meta_UserVote_aasami":true,"Sentences_Meta_UserVote_tonydamage":true,"Sentences_Meta_UserVoteDate_tonydamage":1577999055365,"id":"5a989fd2e0f408eae4151850ed18d1c885b6a20905717915cac35004d46f3f11","last_modified":1577999055767},{"valid":["aasami","tonydamage"],"source":"I am the sole author of these sentences.","invalid":[],"approved":true,"sentence":"Znižuje náklady na hardvérové vybavenie.","username":"aasami","createdAt":1573202375016,"approvalDate":1577999055365,"Sentences_Meta_UserVote_aasami":true,"Sentences_Meta_UserVote_tonydamage":true,"Sentences_Meta_UserVoteDate_tonydamage":1577999055365,"id":"4b1ad18ac20dd0103298300d1a5899c38d893e44667dd3f6c0c393eec44a04c0","last_modified":1577999055723},{"valid":["aasami","tonydamage"],"source":"I am the sole author of these sentences.","invalid":[],"approved":true,"sentence":"To umožňuje efektívnejšie narábať s prebytočným výpočtovým výkonom a dostupným diskovým priestorom.","username":"aasami","createdAt":1573202375015,"approvalDate":1577998968478,"Sentences_Meta_UserVote_aasami":true,"Sentences_Meta_UserVote_tonydamage":true,"Sentences_Meta_UserVoteDate_tonydamage":1577998968478,"id":"1b94c7ea015d6361c8202a47243bf4d800e03b462a0c6eaba0da94f1d8efc221","last_modified":1577998970013},{"valid":["aasami","tonydamage"],"source":"I am the sole author of these sentences.","invalid":[],"approved":true,"sentence":"Dnes veľmi rozšírenou možnosťou je virtualizácia.","username":"aasami","createdAt":1573202375014,"approvalDate":1577998968478,"Sentences_Meta_UserVote_aasami":true,"Sentences_Meta_UserVote_tonydamage":true,"Sentences_Meta_UserVoteDate_tonydamage":1577998968478,"id":"6c7788956f9f41b025c4536cefee45b961cadea0cbbe27eea7ac8af7ee1cc790","last_modified":1577998969972},{"valid":["aasami","tonydamage"],"source":"I am the sole author of these sentences.","invalid":[],"approved":true,"sentence":"V letných mesiacoch tu dochádza pravidelne k prehrievaniu.","username":"aasami","createdAt":1573202375013,"approvalDate":1577998968478,"Sentences_Meta_UserVote_aasami":true,"Sentences_Meta_UserVote_tonydamage":true,"Sentences_Meta_UserVoteDate_tonydamage":1577998968478,"id":"8b7fc7076f14fc24e65c91d0ba32c47ab28f243e31245145cca4c9c3ef6102ab","last_modified":1577998969940},{"valid":["aasami","tonydamage"],"source":"I am the sole author of these sentences.","invalid":[],"approved":true,"sentence":"Zdroj napájania je v prípade dlhších výpadkov napojený na dieselový generátor.","username":"aasami","createdAt":1573202375011,"approvalDate":1577998968478,"Sentences_Meta_UserVote_aasami":true,"Sentences_Meta_UserVote_tonydamage":true,"Sentences_Meta_UserVoteDate_tonydamage":1577998968478,"id":"1972173640566277601d7a72e8c5c8fdd8c510b2be90bde48cab2e6df303d34b","last_modified":1577998969890},{"valid":["aasami","tonydamage"],"source":"I am the sole author of these sentences.","invalid":[],"approved":true,"sentence":"Spolieha sa len na prirodzené vetranie.","username":"aasami","createdAt":1573202375011,"approvalDate":1577998968478,"Sentences_Meta_UserVote_aasami":true,"Sentences_Meta_UserVote_tonydamage":true,"Sentences_Meta_UserVoteDate_tonydamage":1577998968478,"id":"e7265c8f88f7a1394ce089087d821750227cdc2c87d39784effd66331682bc95","last_modified":1577998969855},{"valid":["aasami","tonydamage"],"source":"I am the sole author of these sentences.","invalid":[],"approved":true,"sentence":"Je klimatizovaná viacerými nezávislými klimatizačnými jednotkami.","username":"aasami","createdAt":1573202375009,"approvalDate":1577998968478,"Sentences_Meta_UserVote_aasami":true,"Sentences_Meta_UserVote_tonydamage":true,"Sentences_Meta_UserVoteDate_tonydamage":1577998968478,"id":"0fc4876061276227b7a6675c6db6f4a84f135e40fb740908c403af4c609a1131","last_modified":1577998969802},{"valid":["aasami","tonydamage"],"source":"I am the sole author of these sentences.","invalid":[],"approved":true,"sentence":"Logické jednotky je možné pohodlne zväčšovať podľa aktuálnej potreby.","username":"aasami","createdAt":1573202375008,"approvalDate":1577998968478,"Sentences_Meta_UserVote_aasami":true,"Sentences_Meta_UserVote_tonydamage":true,"Sentences_Meta_UserVoteDate_tonydamage":1577998968478,"id":"c87dfe20e7b1503cb9b919b6a53d6112af38ac63e603a7b39a41f091c3e2f63f","last_modified":1577998969763},{"valid":["aasami","tonydamage"],"source":"I am the sole author of these sentences.","invalid":[],"approved":true,"sentence":"Väčšina vybavenia je umiestnená centrálne na jednom mieste v serverovni.","username":"aasami","createdAt":1573202375008,"approvalDate":1577998968478,"Sentences_Meta_UserVote_aasami":true,"Sentences_Meta_UserVote_tonydamage":true,"Sentences_Meta_UserVoteDate_tonydamage":1577998968478,"id":"636c5c299a41ea6d036e6ec0a72ab30162be5e230664a85a54cdbcbaec1b3b61","last_modified":1577998969744},{"valid":["aasami","tonydamage"],"source":"I am the sole author of these sentences.","invalid":[],"approved":true,"sentence":"Prevádzkové údaje sú uložene na sieťových úložiskách.","username":"aasami","createdAt":1573202375007,"approvalDate":1577998968478,"Sentences_Meta_UserVote_aasami":true,"Sentences_Meta_UserVote_tonydamage":true,"Sentences_Meta_UserVoteDate_tonydamage":1577998968478,"id":"0679d47bc0388edd9b5ee24ac6b539efc01a129f7b2af0a01c5a8166158260cd","last_modified":1577998969715},{"valid":["aasami","tonydamage"],"source":"I am the sole author of these sentences.","invalid":[],"approved":true,"sentence":"Dlhodobým zámerom je uniformita serverovej infraštruktúry orientovaním sa na jednu platformu.","username":"aasami","createdAt":1573202375005,"approvalDate":1577998968478,"Sentences_Meta_UserVote_aasami":true,"Sentences_Meta_UserVote_tonydamage":true,"Sentences_Meta_UserVoteDate_tonydamage":1577998968478,"id":"c0ae90fa0f65c109f385d8d564726a013d23c901f575746319f7f1e8d1eda92e","last_modified":1577998969651},{"valid":["aasami","tonydamage"],"source":"I am the sole author of these sentences.","invalid":[],"approved":true,"sentence":"Zloženie látky nie je homogénne.","username":"aasami","createdAt":1573202375001,"approvalDate":1577998968478,"Sentences_Meta_UserVote_aasami":true,"Sentences_Meta_UserVote_tonydamage":true,"Sentences_Meta_UserVoteDate_tonydamage":1577998968478,"id":"d6f63b6929da4e96ca95b3faa15fe06a71e561768362b1f8ddb23dab0274301f","last_modified":1577998969548},{"valid":["aasami","tonydamage"],"source":"Crafted, from my head.","invalid":[],"approved":true,"sentence":"Ďatelinku som pokosil, teraz mi treba iné obrábať.","username":"aasami","createdAt":1551793337676,"approvalDate":1577998968478,"Sentences_Meta_UserVote_aasami":true,"Sentences_Meta_UserVote_tonydamage":true,"Sentences_Meta_UserVoteDate_tonydamage":1577998968478,"id":"ee5726347009f6c4579e72ab60a294a865b55d0a82e0a550d8909b2a66c63d1a","last_modified":1577998969436},{"valid":["aasami","tonydamage"],"source":"Crafted, from my head.","invalid":[],"approved":true,"sentence":"Obracaj sa gazdiná, kým sa máš pre koho!","username":"aasami","createdAt":1551793337673,"approvalDate":1577998968478,"Sentences_Meta_UserVote_aasami":true,"Sentences_Meta_UserVote_tonydamage":true,"Sentences_Meta_UserVoteDate_tonydamage":1577998968478,"id":"78e1bbc42026fad2ec8e9741ff4c69ebad2042aa81908b9304b9603c2c0e7a67","last_modified":1577998969344},{"valid":["aasami","tonydamage"],"source":"Crafted, from my head.","invalid":[],"approved":true,"sentence":"Len sa mu nevysmievaj aby si sa nesmial naposledy!","username":"aasami","createdAt":1551793337641,"approvalDate":1577998968478,"Sentences_Meta_UserVote_aasami":true,"Sentences_Meta_UserVote_tonydamage":true,"Sentences_Meta_UserVoteDate_tonydamage":1577998968478,"id":"7e48de73b4f84bcb0eed970edcf0041d2296fb5d3d05d17702740097acef136d","last_modified":1577998969285},{"valid":["aasami","tonydamage"],"source":"Crafted, from my head.","invalid":[],"approved":true,"sentence":"Pridáš sa a či budeš ďalej otáľať?","username":"aasami","createdAt":1551793337637,"approvalDate":1577998968478,"Sentences_Meta_UserVote_aasami":true,"Sentences_Meta_UserVote_tonydamage":true,"Sentences_Meta_UserVoteDate_tonydamage":1577998968478,"id":"9682dd5a50ffb64aa58c3835ea3090306518169678cdb6d5c54cbd1f1025e159","last_modified":1577998969218},{"valid":["wosk","aasami"],"source":"My creation","invalid":[],"approved":true,"sentence":"Slovenčina zatiaľ v zbierke nefiguruje, ale pracuje sa na nej.","username":"aasami","createdAt":1551799906351,"approvalDate":1573205840710,"Sentences_Meta_UserVote_wosk":true,"Sentences_Meta_UserVote_aasami":true,"Sentences_Meta_UserVoteDate_wosk":1566763695315,"Sentences_Meta_UserVoteDate_aasami":1573205840710,"id":"6c87d570296dab17c4752cf00c04455dbaf80d52e42ede798db005e322d4b07d","last_modified":1573205841215},{"valid":["aasami","wosk"],"source":"Crafted, from my head.","invalid":[],"approved":true,"sentence":"Vari by ju aj zmárnil, keby som neorodovala.","username":"aasami","createdAt":1551793337668,"approvalDate":1566763695314,"Sentences_Meta_UserVote_wosk":true,"Sentences_Meta_UserVote_aasami":true,"Sentences_Meta_UserVoteDate_wosk":1566763695314,"id":"f64fc4b4b7cb232fbb07493183f987455f1f28ec92a10f0a0d5e48f49b6bad25","last_modified":1566763658574},{"valid":["aasami","wosk"],"source":"Crafted, from my head.","invalid":[],"approved":true,"sentence":"Ej bisťu, vieš sa Ty ale valaškou oháňať!","username":"aasami","createdAt":1551793337664,"approvalDate":1566763695314,"Sentences_Meta_UserVote_wosk":true,"Sentences_Meta_UserVote_aasami":true,"Sentences_Meta_UserVoteDate_wosk":1566763695314,"id":"9419d22054e7902a5a81df0e26cb2a08af0c44893a6fb12db76f79457110d0b5","last_modified":1566763658546},{"valid":["aasami","wosk"],"source":"Crafted, from my head.","invalid":[],"approved":true,"sentence":"Dobre sa Ty poobzeraj, či ťa niekto nešpehuje!","username":"aasami","createdAt":1551793337662,"approvalDate":1566763695314,"Sentences_Meta_UserVote_wosk":true,"Sentences_Meta_UserVote_aasami":true,"Sentences_Meta_UserVoteDate_wosk":1566763695314,"id":"01a32a56e06f8d9f5ffa97207f75e79dd60c69e7c51ac3e633a5cb4024f2144d","last_modified":1566763658516},{"valid":["aasami","wosk"],"source":"Crafted, from my head.","invalid":[],"approved":true,"sentence":"Nože uchop nožnice a vystrihni rukavice!","username":"aasami","createdAt":1551793337654,"approvalDate":1566763695314,"Sentences_Meta_UserVote_wosk":true,"Sentences_Meta_UserVote_aasami":true,"Sentences_Meta_UserVoteDate_wosk":1566763695314,"id":"778937cf37ecb7cc5431ba879d2683d0033dabf55f1911bea8cfb0c13bd19eb4","last_modified":1566763658482},{"valid":["aasami","wosk"],"source":"Crafted, from my head.","invalid":[],"approved":true,"sentence":"Krava sa mi otelila a v maštali už nieto miesta.","username":"aasami","createdAt":1551793337650,"approvalDate":1566763695314,"Sentences_Meta_UserVote_wosk":true,"Sentences_Meta_UserVote_aasami":true,"Sentences_Meta_UserVoteDate_wosk":1566763695314,"id":"03203169e0f738415f90ffbe3bccc20c81b333604935aef8fbc4660dd4dceaca","last_modified":1566763658455},{"valid":["aasami","wosk"],"source":"Crafted, from my head.","invalid":[],"approved":true,"sentence":"Nemám na výber.","username":"aasami","createdAt":1551793337646,"approvalDate":1566763695314,"Sentences_Meta_UserVote_wosk":true,"Sentences_Meta_UserVote_aasami":true,"Sentences_Meta_UserVoteDate_wosk":1566763695314,"id":"e4791ec61b63357913a2efd9f66d0e17ed1c9a72a501655da649fbaa3a8a356a","last_modified":1566763658414},{"valid":["aasami","wosk"],"source":"Crafted, from my head.","invalid":[],"approved":true,"sentence":"No to som si mohol myslieť, že na Teba nie je spoľah.","username":"aasami","createdAt":1551793337629,"approvalDate":1566763695314,"Sentences_Meta_UserVote_wosk":true,"Sentences_Meta_UserVote_aasami":true,"Sentences_Meta_UserVoteDate_wosk":1566763695314,"id":"c83de3217096ef2e7cc04a7d9dca143c3d5cfeb8c7f0ae31e49aa7846fe23981","last_modified":1566763658357},{"valid":["aasami","wosk"],"source":"Crafted, from my head.","invalid":[],"approved":true,"sentence":"Nebodaj by si chcela radšej Paľa ako Ďura?","username":"aasami","createdAt":1551793337614,"approvalDate":1566763695314,"Sentences_Meta_UserVote_wosk":true,"Sentences_Meta_UserVote_aasami":true,"Sentences_Meta_UserVoteDate_wosk":1566763695314,"id":"c448a06a30b7eb73a38c4acfc1d28cb99eb9099b446e4b326f23c79977d5aaa9","last_modified":1566763658321},{"valid":["aasami","wosk"],"source":"Crafted, from my head.","invalid":[],"approved":true,"sentence":"Vyšší počet komponentov zvyšuje pravdepodobnosť výpadkov v dôsledku zlyhania hardvéru.","username":"aasami","createdAt":1551793337609,"approvalDate":1566763695314,"Sentences_Meta_UserVote_wosk":true,"Sentences_Meta_UserVote_aasami":true,"Sentences_Meta_UserVoteDate_wosk":1566763695314,"id":"010c7e925f14de22afdb85f12092fa3c4261b4e9582e4c843a93d3ad7dac483e","last_modified":1566763658292},{"valid":["aasami","wosk"],"source":"Crafted, from my head.","invalid":[],"approved":true,"sentence":"Náklady na vybudovanie infraštruktúry sú niekoľkonásobne vyššie ako pri použití iných alternatív.","username":"aasami","createdAt":1551793337606,"approvalDate":1566763695314,"Sentences_Meta_UserVote_wosk":true,"Sentences_Meta_UserVote_aasami":true,"Sentences_Meta_UserVoteDate_wosk":1566763695314,"id":"8971f77c1f3d1f712521de11f06d2a91a86e2b5f9f7dc916c4ea0e2c927aa100","last_modified":1566763658260}]